pritty_logger/__init__.py
pritty_logger-0.3.4.dist-info/LICENSE
pritty_logger-0.3.4.dist-info/METADATA
pritty_logger-0.3.4.dist-info/WHEEL
pritty_logger-0.3.4.dist-info/top_level.txt
pritty_logger-0.3.4.dist-info/RECORD
