Metadata-Version: 2.1
Name: pritty_logger
Version: 0.3.4
Summary: A logger with rich formatting
Home-page: https://github.com/leon-gorissen/pritty_logger
Author: Leon Gorißen
Author-email: leon.gorissen@gmx.de
Classifier: Programming Language :: Python :: 3
Classifier: License :: OSI Approved :: MIT License
Classifier: Operating System :: POSIX :: Linux
Classifier: Development Status :: 4 - Beta
Classifier: Intended Audience :: Developers
Classifier: Topic :: Software Development :: Libraries :: Python Modules
Requires-Python: >=3.6
License-File: LICENSE
Requires-Dist: rich
